persocial/__init__.py
persocial/admin.py
persocial/apps.py
persocial/migrations/__init__.py
persocial/models/__init__.py
persocial/models/actors.py
persocial/tests.py
persocial-0.1.2.dist-info/LICENSE
persocial-0.1.2.dist-info/WHEEL
persocial-0.1.2.dist-info/METADATA
persocial-0.1.2.dist-info/RECORD
