Metadata-Version: 2.1
Name: persocial
Version: 0.1.2
Summary: 
Author: Robert Townley
Author-email: me@roberttownley.com
Requires-Python: >=3.9,<4.0
Classifier: Programming Language :: Python :: 3
Classifier: Programming Language :: Python :: 3.9
Requires-Dist: Django (>=3.1.4,<4.0.0)
Requires-Dist: wheel (>=0.36.2,<0.37.0)
